colores/__init__.py
colores/core.py
colores-0.1.2.dist-info/LICENSE.md
colores-0.1.2.dist-info/WHEEL
colores-0.1.2.dist-info/METADATA
colores-0.1.2.dist-info/RECORD
