Metadata-Version: 2.1
Name: colores
Version: 0.1.2
Summary: A Wrapper for Colorama
Home-page: https://github.com/UltiRequiem/colores
License: MIT
Keywords: utilities,utils,aesthetic,colors
Author: Eliaz Bobadilla
Author-email: eliaz.bobadilladev@gmail.com
Requires-Python: >=3.7,<4.0
Classifier: License :: OSI Approved :: MIT License
Classifier: Programming Language :: Python :: 3
Classifier: Programming Language :: Python :: 3.7
Classifier: Programming Language :: Python :: 3.8
Classifier: Programming Language :: Python :: 3.9
Requires-Dist: colorama (>=0.4.4,<0.5.0)
Project-URL: Repository, https://github.com/UltiRequiem/colores
